solana_agentkit/__init__.py
solana_agentkit/example.py
solana_agentkit/agent/__init__.py
solana_agentkit/agent/base.py
solana_agentkit/agent/solana_agent.py
solana_agentkit/constants/__init__.py
solana_agentkit/constants/constants.py
solana_agentkit/langchain/__init__.py
solana_agentkit/langchain/tools.py
solana_agentkit/meteora/__init__.py
solana_agentkit/meteora/constants.py
solana_agentkit/meteora/helpers.py
solana_agentkit/meteora/idl.py
solana_agentkit/meteora/types.py
solana_agentkit/meteora/utils.py
solana_agentkit/raydium/__init__.py
solana_agentkit/raydium/constants.py
solana_agentkit/raydium/layouts.py
solana_agentkit/raydium/types.py
solana_agentkit/raydium/utils.py
solana_agentkit/social/__init__.py
solana_agentkit/social/twitter/__init__.py
solana_agentkit/social/twitter/account_details.py
solana_agentkit/social/twitter/account_mentions.py
solana_agentkit/social/twitter/action.py
solana_agentkit/social/twitter/post_tweet.py
solana_agentkit/social/twitter/post_tweet_reply.py
solana_agentkit/tools/__init__.py
solana_agentkit/tools/base.py
solana_agentkit/tools/burn_and_close_account.py
solana_agentkit/tools/create_image.py
solana_agentkit/tools/create_meteora_dlmm_pool.py
solana_agentkit/tools/deploy_collection.py
solana_agentkit/tools/deploy_token.py
solana_agentkit/tools/domains.py
solana_agentkit/tools/fetch_price.py
solana_agentkit/tools/get_balance.py
solana_agentkit/tools/get_token_data.py
solana_agentkit/tools/get_tps.py
solana_agentkit/tools/image.py
solana_agentkit/tools/launch_pumpfun_token.py
solana_agentkit/tools/lend.py
solana_agentkit/tools/nft.py
solana_agentkit/tools/nft_minting.py
solana_agentkit/tools/register_domain.py
solana_agentkit/tools/request_faucet_funds.py
solana_agentkit/tools/stake_with_jup.py
solana_agentkit/tools/tokens.py
solana_agentkit/tools/trade.py
solana_agentkit/tools/trading.py
solana_agentkit/tools/transfer.py
solana_agentkit/tools/use_raydium.py
solana_agentkit/twitter_langchain/__init__.py
solana_agentkit-0.1.3.dist-info/METADATA
solana_agentkit-0.1.3.dist-info/WHEEL
solana_agentkit-0.1.3.dist-info/entry_points.txt
solana_agentkit-0.1.3.dist-info/top_level.txt
solana_agentkit-0.1.3.dist-info/RECORD
