Metadata-Version: 2.1
Name: solana-agentkit
Version: 0.1.3
Summary: A Python toolkit for building AI agents on Solana
Home-page: https://github.com/arhansuba/solana-agentkit
Author: Arhan Subaşı
Author-email: subasiarhan3@gmail.com
Project-URL: Bug Tracker, https://github.com/arhansuba/solana-agentkit/issues
Project-URL: Documentation, https://solana-agentkit.readthedocs.io/
Project-URL: Source Code, https://github.com/arhansuba/solana-agentkit
Keywords: solana,blockchain,artificial-intelligence,ai-agents,cryptocurrency,web3,defi,nft
Classifier: Development Status :: 3 - Alpha
Classifier: Intended Audience :: Developers
Classifier: License :: OSI Approved :: MIT License
Classifier: Operating System :: OS Independent
Classifier: Programming Language :: Python :: 3
Classifier: Programming Language :: Python :: 3.8
Classifier: Programming Language :: Python :: 3.9
Classifier: Programming Language :: Python :: 3.10
Classifier: Topic :: Software Development :: Libraries :: Python Modules
Classifier: Topic :: Internet :: WWW/HTTP
Classifier: Topic :: Scientific/Engineering :: Artificial Intelligence
Requires-Python: >=3.8
Requires-Dist: solana>=0.30.0
Requires-Dist: anchorpy>=0.14.0
Requires-Dist: base58>=2.1.0
Requires-Dist: aiohttp>=3.8.0
Requires-Dist: langchain>=0.0.200
Requires-Dist: openai>=1.0.0
Requires-Dist: python-dotenv>=0.19.0
Requires-Dist: numpy>=1.21.0
Requires-Dist: Pillow>=9.0.0
Requires-Dist: requests>=2.26.0
Requires-Dist: pydantic>=1.8.2
Requires-Dist: web3>=6.0.0
Requires-Dist: cryptography>=3.4.0
Requires-Dist: pytest>=6.2.5
Requires-Dist: pytest-asyncio>=0.18.0
Requires-Dist: typing-extensions>=4.0.0
Provides-Extra: dev
Requires-Dist: black>=22.0.0; extra == "dev"
Requires-Dist: isort>=5.10.0; extra == "dev"
Requires-Dist: mypy>=0.950; extra == "dev"
Requires-Dist: pylint>=2.12.0; extra == "dev"
Requires-Dist: pytest>=6.2.5; extra == "dev"
Requires-Dist: pytest-cov>=3.0.0; extra == "dev"
Requires-Dist: pytest-asyncio>=0.18.0; extra == "dev"
Provides-Extra: docs
Requires-Dist: sphinx>=4.5.0; extra == "docs"
Requires-Dist: sphinx-rtd-theme>=1.0.0; extra == "docs"
Requires-Dist: sphinx-autodoc-typehints>=1.18.0; extra == "docs"
